yta_subtitles_parser/__init__.py
yta_subtitles_parser/dataclasses.py
yta_subtitles_parser/parser.py
yta_subtitles_parser-0.0.1.dist-info/LICENSE
yta_subtitles_parser-0.0.1.dist-info/METADATA
yta_subtitles_parser-0.0.1.dist-info/WHEEL
yta_subtitles_parser-0.0.1.dist-info/RECORD
