Metadata-Version: 2.3
Name: yta-subtitles-parser
Version: 0.0.1
Summary: 
Author: danialcala94
Author-email: danielalcalavalera@gmail.com
Requires-Python: ==3.9
Classifier: Programming Language :: Python :: 3
Classifier: Programming Language :: Python :: 3.9
Requires-Dist: yta_general_utils (>=0.0.262,<1.0.0)
